audio_desilencer/__init__.py
audio_desilencer/audio_processor.py
Audio_DeSilencer-1.0.2.dist-info/LICENSE
Audio_DeSilencer-1.0.2.dist-info/METADATA
Audio_DeSilencer-1.0.2.dist-info/WHEEL
Audio_DeSilencer-1.0.2.dist-info/entry_points.txt
Audio_DeSilencer-1.0.2.dist-info/top_level.txt
Audio_DeSilencer-1.0.2.dist-info/RECORD
